[
  {
    "Id": 1,
    "IdentityNumber": "00000000-0000-0000-0000-000000000000",
    "FirstName": "Orian",
    "LastName": "Markovitz",
    "FullName": "Orian Markovitz",
    "Email": null,
    "PhoneNumber": "054-6589874"
  },
  {
    "Id": 2,
    "IdentityNumber": "00000000-0000-0000-0000-000000000000",
    "FirstName": "Mark",
    "LastName": "Tzukerberg",
    "FullName": "Mark Tzukerberg",
    "Email": null,
    "PhoneNumber": "054-6589874"
  },
  {
    "Id": 1,
    "IdentityNumber": "00000000-0000-0000-0000-000000000000",
    "FirstName": "Stive",
    "LastName": "Jhones",
    "FullName": "Stive Jhones",
    "Email": null,
    "PhoneNumber": "054-6589874"
  },
  {
    "Id": 1,
    "IdentityNumber": "00000000-0000-0000-0000-000000000000",
    "FirstName": "Jeff",
    "LastName": "Bassos",
    "FullName": "Jeff Bassos",
    "Email": null,
    "PhoneNumber": "054-6589874"
  },
  {
    "Id": 5,
    "IdentityNumber": "123456789",
    "FirstName": "rotem",
    "LastName": "dan",
    "FullName": "rotem dan",
    "Email": "rotemd@gmail.com",
    "PhoneNumber": "0551238495"
  }
]